qlikutils/__init__.py
qlikutils/__main__.py
qlikutils/utils.py
qlikutils/assets/__init__.py
qlikutils/assets/fonts/Rubik-Medium.ttf
qlikutils/assets/fonts/Rubik-Regular.ttf
qlikutils/assets/images/background.png
qlikutils-1.1.20.dist-info/LICENSE
qlikutils-1.1.20.dist-info/METADATA
qlikutils-1.1.20.dist-info/WHEEL
qlikutils-1.1.20.dist-info/top_level.txt
qlikutils-1.1.20.dist-info/RECORD
