Metadata-Version: 2.1
Name: qlikutils
Version: 1.1.20
Summary: Toolkit to use with Qlik
Author: Kin Torres
Author-email: kin.mello@gmail.com
Classifier: Programming Language :: Python :: 3
Classifier: License :: OSI Approved :: MIT License
Classifier: Operating System :: OS Independent
Requires-Python: >=3.6
License-File: LICENSE
Requires-Dist: Pillow
